{"type": "地方政务", "title": "广东产业升级在路上 智慧型经济体显雏形", "link": "http://gov.163.com/14/0721/15/A1MHRIAH00234KIR.html"}
{"type": "地方政务", "title": "珠三角拿什么迎接转型拐点？", "link": "http://gov.163.com/14/0721/10/A1M13ITK00234KIR.html"}
{"type": "地方政务", "title": "信息化改造助“老鸟”凤凰涅槃", "link": "http://gov.163.com/14/0721/10/A1M0Q9EN00234KIR.html"}
{"type": "地方政务", "title": "保税区创新管理带到区域升级", "link": "http://gov.163.com/14/0721/10/A1M0OKH500234KIR.html"}
{"type": "地方政务", "title": "粤东西北经济增速快于珠三角", "link": "http://gov.163.com/14/0721/10/A1LV6HI200234KIR.html"}
{"type": "地方政务", "title": "珠三角转型升级对广东意味着什么", "link": "http://gov.163.com/14/0721/10/A1LV0SOL00234KIR.html"}
{"type": "地方政务", "title": "机构改革为广东注入内生新动力", "link": "http://gov.163.com/14/0721/10/A1LUV0AU00234KIR.html"}
{"type": "地方政务", "title": "中线行-湖北郧县生态移民促脱贫致富", "link": "http://gov.163.com/14/0623/10/9VDTQJOJ00234KE7.html"}
{"type": "地方政务", "title": "[新北]5·18四大活动 浙大兰州交大川大全入驻", "link": "http://gov.163.com/14/0513/12/9S4IDDN200234IGH.html"}
{"type": "地方政务", "title": "常州\"三化\"并举发挥最大效用", "link": "http://gov.163.com/14/0513/12/9S4IA23M00234IGH.html"}
{"type": "地方政务", "title": "8年来，1000多个项目落户常州", "link": "http://gov.163.com/14/0513/12/9S4I6P7G00234IGH.html"}
{"type": "地方政务", "title": "\"天天5·18\"网站筹备中 今年展洽会有96场活动", "link": "http://gov.163.com/14/0513/12/9S4I4D1S00234IGH.html"}
{"type": "地方政务", "title": "单纯民间商事案 何必上升到政治？", "link": "http://gov.163.com/14/0422/18/9QF47AQJ00234II0.html"}
{"type": "地方政务", "title": "山东省公安量化277种处罚标准 挡住“说情风”", "link": "http://gov.163.com/14/0311/10/9N231A5300234IGH.html"}
{"type": "地方政务", "title": "江西省开全国先河 援助单亲家庭未成年子女", "link": "http://gov.163.com/14/0311/10/9N22UV4000234IGH.html"}
{"type": "地方政务", "title": "吉林构建长效机制啃民生领域“硬骨头”", "link": "http://gov.163.com/14/0311/10/9N22LQB300234IGH.html"}
{"type": "地方政务", "title": "山西“四级”筹资800余万元保护宋金古建大悲院", "link": "http://gov.163.com/14/0311/10/9N22K1DF00234IKA.html"}
{"type": "地方政务", "title": "河北“重霾城市”邢台削减七大主导产业落后产能", "link": "http://gov.163.com/14/0311/10/9N22IDL800234IGH.html"}
{"type": "地方政务", "title": "天津私人购买新能源车可获免费牌照和政府补贴", "link": "http://gov.163.com/14/0311/10/9N22G5TD00234IGH.html"}
{"type": "地方政务", "title": "内蒙古提前两年半实现城乡居民养老保险并轨", "link": "http://gov.163.com/14/0220/15/9LHMOLGJ00234IGH.html"}
{"type": "地方政务", "title": "新疆：文化交流与融合 生生不息的丝路之魂", "link": "http://gov.163.com/14/0220/15/9LHMLL6500234IKA.html"}
{"type": "地方政务", "title": "新疆已建成92万多户安居富民房 农牧民喜迁新居", "link": "http://gov.163.com/14/0220/15/9LHMJJ9800234IGH.html"}
{"type": "地方政务", "title": "2014年西藏力争落实少数民族发展资金4.5亿元", "link": "http://gov.163.com/14/0220/15/9LHMH3R300234IGH.html"}
{"type": "地方政务", "title": "西藏启动藏医药申遗工作 已正式上报文化部", "link": "http://gov.163.com/14/0220/15/9LHMFBTE00234IGH.html"}
{"type": "地方政务", "title": "陕西纪委:原保留的35个议事协调机构缩减为10个", "link": "http://gov.163.com/14/0220/15/9LHMCROC00234IGH.html"}
{"type": "地方政务", "title": "山东今后5年将培训600万名劳动者 打破地域限制", "link": "http://gov.163.com/14/0219/14/9LF2VI1600234IGH.html"}
{"type": "地方政务", "title": "山东将划永久基本农田 城市“摊饼式”扩张受限", "link": "http://gov.163.com/14/0219/14/9LF2TJQ500234IGH.html"}
{"type": "地方政务", "title": "福建专项整治重污染企业 未批先建企业将被停产", "link": "http://gov.163.com/14/0219/14/9LF2R7RB00234IGH.html"}
{"type": "地方政务", "title": "安徽：城镇园林绿化提升行动启动", "link": "http://gov.163.com/14/0219/14/9LF2KE6S00234IGH.html"}
{"type": "地方政务", "title": "浙江食品安全严打行动将启动 七类食品重点打击", "link": "http://gov.163.com/14/0219/14/9LF2FEGR00234IGH.html"}
{"type": "地方政务", "title": "自贸区首个金融细则落地 跨境人民币支付业务启 ", "link": "http://gov.163.com/14/0219/14/9LF2ADGR00234IGJ.html"}
{"type": "地方政务", "title": "吉林开通“12350”举报电话 鼓励群众监督安全生", "link": "http://gov.163.com/14/0219/14/9LF27BAQ00234IGH.html"}
{"type": "地方政务", "title": "山西财政将投资500万元对古村落实施保护性抢救", "link": "http://gov.163.com/14/0219/14/9LF20M5H00234IGH.html"}
{"type": "地方政务", "title": "山西下拨34.5亿元粮食补贴 3月15日前全部下发", "link": "http://gov.163.com/14/0219/14/9LF1O84000234IGH.html"}
{"type": "地方政务", "title": "河北工业转型治霾 到2017年将削减6000万吨钢铁", "link": "http://gov.163.com/14/0219/14/9LF1M3B600234IGH.html"}
{"type": "地方政务", "title": "湖南严肃“两会”纪律 设督导组公布举报电话", "link": "http://gov.163.com/14/0210/09/9KNBCEH600234IGH.html"}
{"type": "地方政务", "title": "广西计划3年投38亿升级巴马长寿养生国际旅游区", "link": "http://gov.163.com/14/0208/15/9KIPKK1400234IGJ.html"}
{"type": "地方政务", "title": "山东省部分农村承包地状况变 土地确权须治杂症", "link": "http://gov.163.com/14/0208/15/9KIPHK4200234IGJ.html"}
{"type": "地方政务", "title": "山东出台措施全面打造一刻钟便民生活服务圈", "link": "http://gov.163.com/14/0208/15/9KIPG7E500234IGJ.html"}
{"type": "地方政务", "title": "春节期间江西汽车销售增速最劲 平价餐饮成主流", "link": "http://gov.163.com/14/0208/15/9KIPEPG200234IGJ.html"}
{"type": "地方政务", "title": "海峡两岸民俗文化节农历正月十三福州揭幕", "link": "http://gov.163.com/14/0208/15/9KIPD8AM00234IKA.html"}
{"type": "地方政务", "title": "福建八措施方便市民出行 将建出租车电召系统", "link": "http://gov.163.com/14/0208/15/9KIPAVJ500234IGH.html"}
{"type": "地方政务", "title": "安徽将实施33项民生工程 大病保险等新纳入其中", "link": "http://gov.163.com/14/0208/15/9KIP9T0V00234IGH.html"}
{"type": "地方政务", "title": "浙江均富水平再提升 11市农民人均纯收入超万元", "link": "http://gov.163.com/14/0208/15/9KIP8BU500234IGJ.html"}
{"type": "地方政务", "title": "浙江神格2014年将全面实施清洁能源专项行动计划", "link": "http://gov.163.com/14/0208/15/9KIP69MD00234IGJ.html"}
{"type": "地方政务", "title": "江苏省级三公6年零增长 将探索反浪费长效机制", "link": "http://gov.163.com/14/0208/15/9KIP4CI900234IGH.html"}
{"type": "地方政务", "title": "上海今年底4G网络将覆盖中心城区", "link": "http://gov.163.com/14/0208/14/9KIP0B1G00234IGH.html"}
{"type": "地方政务", "title": "上海研制成功H7N9禽流感基因疫苗 下月或临床试 ", "link": "http://gov.163.com/14/0208/14/9KIOVBF300234IGH.html"}
{"type": "地方政务", "title": "上海自贸区提前进入工作状态 办事窗口全部开启", "link": "http://gov.163.com/14/0208/14/9KIOUI7100234IGH.html"}
{"type": "地方政务", "title": "辽宁省今年年底前省内二级以上医院将通用健康卡", "link": "http://gov.163.com/14/0208/14/9KIN5H2T00234IGH.html"}
{"type": "地方政务", "title": "山西各政府机关窗口单位：上班首日 为民忙", "link": "http://gov.163.com/14/0208/14/9KIN24NT00234IGH.html"}
{"type": "地方政务", "title": "冀开展严肃工作纪律检查 重点查迟到早退串岗等", "link": "http://gov.163.com/14/0208/14/9KIMVL0I00234IGH.html"}
{"type": "地方政务", "title": "天津：9人以下乘用车车船税减征2个月", "link": "http://gov.163.com/14/0208/14/9KIMT4J700234IGH.html"}
{"type": "地方政务", "title": "天津市提高一至四级残疾军人护理费", "link": "http://gov.163.com/14/0208/14/9KIMSAFK00234IGH.html"}
{"type": "地方政务", "title": "四川将划定森林林地等保护红线 营造林600万亩", "link": "http://gov.163.com/14/0126/15/9JHD616F00234IGH.html"}
{"type": "地方政务", "title": "四川：市级检察院6月底前全部完成门户网站建设", "link": "http://gov.163.com/14/0126/15/9JHD4D8400234IGH.html"}
{"type": "地方政务", "title": "海口将打造省现代服务业中心 推六大旅游品牌", "link": "http://gov.163.com/14/0126/15/9JHD0H1R00234IGJ.html"}
{"type": "地方政务", "title": "海南省食品药品监管体制实行改革 告别多头监管", "link": "http://gov.163.com/14/0126/15/9JHCVGEV00234IGH.html"}
{"type": "地方政务", "title": "广西去年投入284亿元支持深化医药卫生体制改革", "link": "http://gov.163.com/14/0126/15/9JHCTQHS00234IGH.html"}
{"type": "地方政务", "title": "去年河南省电商交易达4200亿 同比增长30%以上", "link": "http://gov.163.com/14/0126/15/9JHCLCFE00234IGJ.html"}
{"type": "地方政务", "title": "河南省各类市场主体总量达258.1万户", "link": "http://gov.163.com/14/0126/15/9JHCGMCK00234IGJ.html"}
{"type": "地方政务", "title": "山东将在部分市试点开展蔬菜生猪目标价格保险", "link": "http://gov.163.com/14/0126/15/9JHCEHDI00234IGH.html"}
{"type": "地方政务", "title": "山东省博物馆木版年画展开展 32米巨幅年画亮相", "link": "http://gov.163.com/14/0126/15/9JHCD7EQ00234IKA.html"}
{"type": "地方政务", "title": "安徽省出台新规：省级机关必须安排残疾人就业", "link": "http://gov.163.com/14/0126/15/9JHC3J3Q00234IGH.html"}
{"type": "地方政务", "title": "江苏省率先启动“廉洁国企”建设 通报典型案件", "link": "http://gov.163.com/14/0126/15/9JHC1MJH00234IGH.html"}
{"type": "地方政务", "title": "苏州百年老校超110所 成立协会推动其立法保护", "link": "http://gov.163.com/14/0126/15/9JHC0DB400234IKA.html"}
{"type": "地方政务", "title": "上海器官捐献系统启动至今 目前已有9个成功案例", "link": "http://gov.163.com/14/0126/15/9JHBVDDN00234IGH.html"}
{"type": "地方政务", "title": "年初一起至4月底暂停 上海将逐步取消活禽交易", "link": "http://gov.163.com/14/0126/15/9JHBUH3500234IGH.html"}
{"type": "地方政务", "title": "吉林加大春运监管力度10天输送旅客746万人次", "link": "http://gov.163.com/14/0126/15/9JHBSUAO00234IGH.html"}
{"type": "地方政务", "title": "44个景区邀您“到吉林过大年” 9景区有优惠", "link": "http://gov.163.com/14/0126/15/9JHBR4P600234IGH.html"}
{"type": "地方政务", "title": "辽宁省全国重点文物保护单位共有128处", "link": "http://gov.163.com/14/0126/15/9JHBQ26S00234IGH.html"}
{"type": "地方政务", "title": "辽宁省劳动争议案件80%涉及民企", "link": "http://gov.163.com/14/0126/15/9JHBP3LC00234IGH.html"}
{"type": "地方政务", "title": "河北省财政68.3亿惠农补贴促春耕", "link": "http://gov.163.com/14/0126/15/9JHBNEIP00234IGJ.html"}
{"type": "地方政务", "title": "天津市自行车产业规模力争2017年达1400亿元", "link": "http://gov.163.com/14/0126/15/9JHBLMDP00234IGJ.html"}
{"type": "地方政务", "title": "云南铁路大通道建设加速 去年铁路投资超260亿元", "link": "http://gov.163.com/14/0107/15/9I0FHSBL00234IGJ.html"}
{"type": "地方政务", "title": "贵州固定资产投资保持较快增长势头", "link": "http://gov.163.com/14/0107/15/9I0FGFHV00234IGJ.html"}
{"type": "地方政务", "title": "四川八大举措治理空气污染 对各级政府考核问责", "link": "http://gov.163.com/14/0107/15/9I0FDK6Q00234IGH.html"}
{"type": "地方政务", "title": "2014年四川将继续实施“十项民生工程”", "link": "http://gov.163.com/14/0107/15/9I0FCE1H00234IGH.html"}
{"type": "地方政务", "title": "2013重庆外贸出口成绩单 重庆造日挣1.24亿美元", "link": "http://gov.163.com/14/0107/15/9I0FB35G00234IGJ.html"}
{"type": "地方政务", "title": "海口市两产业集群提前过百亿元 港航物流成黑马", "link": "http://gov.163.com/14/0107/15/9I0F6J8500234IGJ.html"}
{"type": "地方政务", "title": "湖南2013年度500千伏直流融冰工程顺利竣工", "link": "http://gov.163.com/14/0107/15/9I0F0UB000234IGH.html"}
{"type": "地方政务", "title": "湖南13个单位统计违法不真实被通报 并责令改正", "link": "http://gov.163.com/14/0107/15/9I0ETTEO00234IGH.html"}
{"type": "地方政务", "title": "湖南第二届网络文化节 \"湖南特产\"走向全球网友", "link": "http://gov.163.com/14/0107/15/9I0EST4S00234IKA.html"}
{"type": "地方政务", "title": "2013年河南建成高标准农田970多万亩 保障生产力", "link": "http://gov.163.com/14/0107/15/9I0DRUCT00234IGH.html"}
{"type": "地方政务", "title": "江西南昌市首次明确2018年基本形成1小时经济圈", "link": "http://gov.163.com/14/0107/15/9I0DO81300234IGJ.html"}
{"type": "地方政务", "title": "安徽磬云山入选国家地质公园 地貌造型罕见", "link": "http://gov.163.com/14/0107/15/9I0DMGN200234IKA.html"}
{"type": "地方政务", "title": "江苏省教育现代化建设监测评估工作启动", "link": "http://gov.163.com/14/0107/15/9I0DH43D00234IGH.html"}
{"type": "地方政务", "title": "上海自贸区迎来“百日” 制度创新释放改革红利", "link": "http://gov.163.com/14/0107/15/9I0DBNIC00234IGJ.html"}
{"type": "地方政务", "title": "吉林省部署重点任务构筑食品药品安全监管防线", "link": "http://gov.163.com/14/0107/14/9I0BLER500234IGH.html"}
{"type": "地方政务", "title": "湖南省航空口岸年度出入境人数首度破100万人次", "link": "http://gov.163.com/13/1211/15/9FQT6GJI00234IGJ.html"}
{"type": "地方政务", "title": "山东增强内生动力推进“家门口的城镇化”", "link": "http://gov.163.com/13/1211/15/9FQT0J0C00234IGJ.html"}
{"type": "地方政务", "title": "江西将统一招聘幼儿教师 在岗无证幼师五年过渡", "link": "http://gov.163.com/13/1211/15/9FQST1HN00234IGH.html"}
{"type": "地方政务", "title": "江西景德镇南窑发现唐代最长的龙窑遗迹", "link": "http://gov.163.com/13/1211/15/9FQSS52U00234IKA.html"}
{"type": "地方政务", "title": "福建省山洪灾害防治县级非工程措施项目建成", "link": "http://gov.163.com/13/1211/15/9FQSPPFT00234IGH.html"}
{"type": "地方政务", "title": "安徽省首批国家级出口食品示范区实现零退货", "link": "http://gov.163.com/13/1211/15/9FQSNHGG00234IGJ.html"}
{"type": "地方政务", "title": "浙江省首条水底高速公路钱江通道 预计月底通车", "link": "http://gov.163.com/13/1211/15/9FQSMBL300234IGH.html"}
{"type": "地方政务", "title": "江苏省推行电梯责任险 将按楼层和“年龄”缴费", "link": "http://gov.163.com/13/1211/15/9FQSL21J00234IGH.html"}
{"type": "地方政务", "title": "河北省残疾人远程教育项目启动 可就近免费培训", "link": "http://gov.163.com/13/1211/15/9FQSFUDC00234IGH.html"}
{"type": "地方政务", "title": "山西省直单位公车燃油费用公务卡结算", "link": "http://gov.163.com/13/1211/15/9FQSDVGJ00234IGH.html"}
{"type": "地方政务", "title": "安徽省出台六条举措壮大“专精特新”中小企业", "link": "http://gov.163.com/13/1205/14/9FBB1GHL00234IGJ.html"}
{"type": "地方政务", "title": "浙江推动立法项目实施接地气 建基层联系点制度", "link": "http://gov.163.com/13/1205/14/9FBAV54K00234IGH.html"}
{"type": "地方政务", "title": "浙江省将试行立法审议辩论和个别条款表决制度", "link": "http://gov.163.com/13/1205/14/9FBATEP400234IGH.html"}
{"type": "地方政务", "title": "沪公立医院拟剥离特需服务 进入两个国际医学园", "link": "http://gov.163.com/13/1205/14/9FBARN9C00234IGH.html"}
{"type": "地方政务", "title": "河北大气污染防治专项检查 明查暗查夜查相结合", "link": "http://gov.163.com/13/1205/14/9FBAO9DE00234IGH.html"}
{"type": "地方政务", "title": "现存中国最早佛阁实例现身山西太原龙山", "link": "http://gov.163.com/13/1205/13/9FB8UP1P00234IKA.html"}
{"type": "地方政务", "title": "贵州省启动冬季交通安全攻坚 客运车辆逢车必检", "link": "http://gov.163.com/13/1203/15/9F6AL1A200234IGH.html"}
{"type": "地方政务", "title": "重庆微企参加会展可获多项补助 每年最高可获3万", "link": "http://gov.163.com/13/1203/15/9F6ADEB800234IGJ.html"}
{"type": "地方政务", "title": "海南：恶意欠薪情节严重单位将被吊销营业执照", "link": "http://gov.163.com/13/1203/15/9F6ABBSG00234IGH.html"}
{"type": "地方政务", "title": "长沙部署油气管网安全工作 五油气管道贯穿长沙", "link": "http://gov.163.com/13/1203/15/9F6AA4ES00234IGH.html"}
{"type": "地方政务", "title": "武汉计划280亿元治理空气 2016年淘汰所有黄标车", "link": "http://gov.163.com/13/1203/15/9F6A303F00234IGH.html"}
{"type": "地方政务", "title": "福建启动商事登记制度改革 引台商投资热潮", "link": "http://gov.163.com/13/1203/15/9F6A18FT00234IGJ.html"}
{"type": "地方政务", "title": "河南：种植大户成粮食增产重要保障", "link": "http://gov.163.com/13/1203/15/9F69C3CF00234IGJ.html"}
{"type": "地方政务", "title": "安徽省13个县试点参合农民刷“二代身份证”就诊", "link": "http://gov.163.com/13/1203/14/9F66P9OU00234IGH.html"}
{"type": "地方政务", "title": "江苏省工业利润前10个月5707亿元 同比增长18.8%", "link": "http://gov.163.com/13/1203/14/9F66H8UN00234IGJ.html"}
{"type": "地方政务", "title": "上海逾515万市民\"人户分离\" 占户籍人口总数36.1", "link": "http://gov.163.com/13/1203/14/9F66E53000234IGH.html"}
{"type": "地方政务", "title": "台专家：“辽宁号”过台湾海峡 两岸有默契", "link": "http://gov.163.com/13/1203/11/9F5RIUIO00234II0.html"}
{"type": "地方政务", "title": "湖南在深圳设产品展销中心 湘品出湘再迈新步", "link": "http://gov.163.com/13/1125/14/9EHK19PO00234IGJ.html"}
{"type": "地方政务", "title": "河南新农合大病二次报销试点将扩容明年增4到6个", "link": "http://gov.163.com/13/1125/14/9EHJUQDG00234IGH.html"}
{"type": "地方政务", "title": "江西出台规定 引入社会力量监督分设“重点班”", "link": "http://gov.163.com/13/1125/14/9EHJQMFI00234IGH.html"}
{"type": "地方政务", "title": "天津市家庭服务业电子商务平台12月中旬有望上线", "link": "http://gov.163.com/13/1125/14/9EHJIE7P00234IGH.html"}
{"type": "地方政务", "title": "杭州生态红线将进入立法阶段 新项目跨线将否决", "link": "http://gov.163.com/13/1125/14/9EHJFU0N00234IGH.html"}
{"type": "地方政务", "title": "安徽省委组织部聚焦“四风”促整改求实效", "link": "http://gov.163.com/13/1125/14/9EHJE6L100234IGH.html"}
{"type": "地方政务", "title": "吉林：严禁乱检查等干扰和影响基层企业工作行为", "link": "http://gov.163.com/13/1125/14/9EHJCNVK00234IGH.html"}
{"type": "地方政务", "title": "山西太原：每千名农村户籍人口配备2名乡村医生", "link": "http://gov.163.com/13/1125/14/9EHJ82FI00234IGH.html"}
{"type": "地方政务", "title": "河北省拆除8家钢铁企业10座高炉16座转炉", "link": "http://gov.163.com/13/1125/14/9EHJ512F00234IGH.html"}
{"type": "地方政务", "title": "湖北省挂牌督办23家环境违法企业 责令限期整改", "link": "http://gov.163.com/13/1107/16/9D3E2PV900234IGJ.html"}
{"type": "地方政务", "title": "河南省学前教育三年行动计划今年“收官”", "link": "http://gov.163.com/13/1107/16/9D3E1BJO00234IGH.html"}
{"type": "地方政务", "title": "山东快递业务旺季监测启动 遇纠纷可拨12305", "link": "http://gov.163.com/13/1107/16/9D3E08JA00234IGJ.html"}
{"type": "地方政务", "title": "浙江出文件：人民政协可以十种形式加强民主监督", "link": "http://gov.163.com/13/1107/16/9D3DTDSR00234IGH.html"}
{"type": "地方政务", "title": "江苏南京已在研究重污染天企事业单位弹性工作制", "link": "http://gov.163.com/13/1107/16/9D3DRDSA00234IGH.html"}
{"type": "地方政务", "title": "安徽出口免验企业增至7家 总数居中部之首", "link": "http://gov.163.com/13/1107/16/9D3DOKS900234IGJ.html"}
{"type": "地方政务", "title": "吉林省民营企业探索“教授经济” 破解人才瓶颈", "link": "http://gov.163.com/13/1107/16/9D3DMRF400234IGJ.html"}
{"type": "地方政务", "title": "山西煤炭开采生态补偿机制将法律化", "link": "http://gov.163.com/13/1107/16/9D3DLJTU00234IGH.html"}
{"type": "地方政务", "title": "两化融合提速 重庆制造迈向智慧工厂 多企业掘金", "link": "http://gov.163.com/13/1105/14/9CU51Q3H00234IGJ.html"}
{"type": "地方政务", "title": "海南将建296个幸福院 破解农村留守老人养老难题", "link": "http://gov.163.com/13/1105/14/9CU4V6UH00234IGH.html"}
{"type": "地方政务", "title": "河南省经济呈现稳中向好态势 城乡居民腰包渐鼓", "link": "http://gov.163.com/13/1105/14/9CU4S93400234IGJ.html"}
{"type": "地方政务", "title": "山东出台扶持服务业发展“30条” 商业电价优惠", "link": "http://gov.163.com/13/1105/14/9CU4QK7H00234IGJ.html"}
{"type": "地方政务", "title": "江西省拟建广昌至吉安高速公路 途经6个县区", "link": "http://gov.163.com/13/1105/14/9CU4P81Q00234IGH.html"}
{"type": "地方政务", "title": "科技成果转化率提高 科技创新为江西经济助跑", "link": "http://gov.163.com/13/1105/14/9CU4O83U00234IGJ.html"}
{"type": "地方政务", "title": "安徽：“建设财政”转向“民生财政”", "link": "http://gov.163.com/13/1105/14/9CU4LF4300234IGH.html"}
{"type": "地方政务", "title": "安徽省停止审批政府性楼堂馆所", "link": "http://gov.163.com/13/1105/14/9CU4KKD400234IGH.html"}
{"type": "地方政务", "title": "江苏：力争开建沪通铁路 苏南地区协同控制PM2.5", "link": "http://gov.163.com/13/1105/14/9CU4GBAH00234IGH.html"}
{"type": "地方政务", "title": "天津打造系列文化工程 自然博物馆新馆下月开放", "link": "http://gov.163.com/13/1105/14/9CU47JB000234IGJ.html"}
{"type": "地方政务", "title": "四川新规：农家乐纳入旅馆管理 入住要实名登记", "link": "http://gov.163.com/13/1101/14/9CJQN48200234IGJ.html"}
{"type": "地方政务", "title": "广西成功签发全国首份出口电力优惠性原产地证书", "link": "http://gov.163.com/13/1101/14/9CJQJNUR00234IGJ.html"}
{"type": "地方政务", "title": "湖北3D打印产业规划即将出炉 东湖高新建产业园", "link": "http://gov.163.com/13/1101/14/9CJQG7FA00234IGJ.html"}
{"type": "地方政务", "title": "坚持加速转型 江西经济稳中向好演绎“升级版”", "link": "http://gov.163.com/13/1101/14/9CJQBQA600234IGJ.html"}
{"type": "地方政务", "title": "上海自贸区改革红利初显 着力打造宽进严管环境", "link": "http://gov.163.com/13/1101/14/9CJP6IKU00234IGJ.html"}
{"type": "地方政务", "title": "吉林绕城高速路建成通车 延吉去沈阳节省40公里", "link": "http://gov.163.com/13/1101/14/9CJP117800234IGH.html"}
{"type": "地方政务", "title": "山西文化惠民设施设备下基层 流动服务车全覆盖", "link": "http://gov.163.com/13/1101/14/9CJOU3NP00234IGH.html"}
{"type": "地方政务", "title": "天津：幼儿园提前教授小学内容将批评并责令整改", "link": "http://gov.163.com/13/1101/14/9CJOP6V900234IGH.html"}
{"type": "地方政务", "title": "陕西将开展校车安全专项督查 确保学生交通安全", "link": "http://gov.163.com/13/1028/15/9C9L82OO00234IGH.html"}
{"type": "地方政务", "title": "政金企联合打造融资平台助力贵州能源行业大发展", "link": "http://gov.163.com/13/1028/15/9C9L5CKH00234IGJ.html"}
{"type": "地方政务", "title": "丽攀高速 四川和云南都在动", "link": "http://gov.163.com/13/1028/15/9C9KS0RA00234IGH.html"}
{"type": "地方政务", "title": "成都至昆明实现全程高速", "link": "http://gov.163.com/13/1028/15/9C9KR7RM00234IGH.html"}
{"type": "地方政务", "title": "2015年湖南80%城乡居民有望拥有全国统一健康卡", "link": "http://gov.163.com/13/1028/15/9C9KPPEV00234IGH.html"}
{"type": "地方政务", "title": "河南省：500多亿资金“灌溉”8000家中小企业", "link": "http://gov.163.com/13/1028/15/9C9KND6B00234IGJ.html"}
{"type": "地方政务", "title": "山东省23个省直部门1-5月份8项经费同比减26.5%", "link": "http://gov.163.com/13/1028/15/9C9KLI1D00234IGH.html"}
{"type": "地方政务", "title": "安徽省人大常委会将每月10日定为代表接待日", "link": "http://gov.163.com/13/1028/15/9C9KJNJS00234IGH.html"}
{"type": "地方政务", "title": "浙江高校获专业设置“自主权\" 不再依靠行政拍板", "link": "http://gov.163.com/13/1028/15/9C9K4DTE00234IGH.html"}
{"type": "地方政务", "title": "中国工程机械“333100互动圆梦工程”在湖南启动", "link": "http://gov.163.com/13/1025/10/9C1BM3K300234IGJ.html"}
{"type": "地方政务", "title": "杭州推新能源交通 新能源车：年底再推两三百辆", "link": "http://gov.163.com/13/1025/10/9C1BIAAU00234IGJ.html"}
{"type": "地方政务", "title": "天津：投资19.2亿治995个入河排污口门控源截污", "link": "http://gov.163.com/13/1025/10/9C1BF64200234IGJ.html"}
{"type": "地方政务", "title": "安徽前三季度实际利用外资87亿美元 同比增23.3%", "link": "http://gov.163.com/13/1022/15/9BQ49RDT00234IGJ.html"}
{"type": "地方政务", "title": "榕40个项目赴文博会招商 琅岐国际旅游岛投200亿", "link": "http://gov.163.com/13/1022/15/9BQ47IJ900234IGJ.html"}
{"type": "地方政务", "title": "河南省促社工服务社会化专业化 五类人群将受益", "link": "http://gov.163.com/13/1022/15/9BQ40OHN00234IGH.html"}
{"type": "地方政务", "title": "广西明年底异地就医即时结算 北部湾4市年内实现", "link": "http://gov.163.com/13/1022/15/9BQ3VFFC00234IGH.html"}
{"type": "地方政务", "title": "上半年沪金融景气指数发布 人才引进显浦东引力", "link": "http://gov.163.com/13/1022/15/9BQ3SBAT00234IGJ.html"}
{"type": "地方政务", "title": "山东省发布污水处理规划 市县出水要达一级A标准", "link": "http://gov.163.com/13/1022/14/9BQ3I4NJ00234IGH.html"}
{"type": "地方政务", "title": "广东明年高考保送政策收紧 取消奥赛等17项加分", "link": "http://gov.163.com/13/1018/15/9BFS25SN00234IGH.html"}
{"type": "地方政务", "title": "天津滨海新区战略性新兴产业实现规模发展", "link": "http://gov.163.com/13/1018/15/9BFRAQP900234IGJ.html"}
{"type": "地方政务", "title": "山东省明确低保标准测算方式 对申请者入户调查", "link": "http://gov.163.com/13/1018/15/9BFR2CRH00234IGH.html"}
{"type": "地方政务", "title": "江西加快加气站建设 南昌明年将建成41座加气站", "link": "http://gov.163.com/13/1018/15/9BFR09NC00234IGH.html"}
{"type": "地方政务", "title": "上海自贸区负面清单适时调整 开放程度前所未有", "link": "http://gov.163.com/13/1018/15/9BFQNTE300234IGJ.html"}
{"type": "地方政务", "title": "国宝永乐宫壁画现“疾病”正着手搬迁后首次修缮", "link": "http://gov.163.com/13/1018/15/9BFQH0K200234IKA.html"}
{"type": "地方政务", "title": "安徽省能源产业效益好转 宏观经济趋稳向好", "link": "http://gov.163.com/13/1018/14/9BFPUDCO00234IGJ.html"}
{"type": "地方政务", "title": "河北拍摄公益宣传片 倡导网络关爱青少年", "link": "http://gov.163.com/13/1016/13/9BAEJ4LN00234JQ7.html"}
{"type": "地方政务", "title": "山东潍坊：如诗似画白浪河", "link": "http://gov.163.com/13/1015/15/9B83GC1E00234JF4.html"}
{"type": "地方政务", "title": "上海自由贸易区挂牌后首批受理企业获颁营业执照", "link": "http://gov.163.com/13/1015/11/9B7NDB1S00234IGJ.html"}
{"type": "地方政务", "title": "山东省创新养老模式 每年财政列拨10亿扶持养老", "link": "http://gov.163.com/13/1014/14/9B5FLVKQ00234IGH.html"}
{"type": "地方政务", "title": "湖南贵州将合力构建一日可通达湘黔经济圈", "link": "http://gov.163.com/13/1014/14/9B5E8G2900234IGJ.html"}
{"type": "地方政务", "title": "安徽为期四月安全生产大检查关闭非法企业315家", "link": "http://gov.163.com/13/1014/14/9B5DNT7S00234IGH.html"}
{"type": "地方政务", "title": "重庆将打造西部电子信息与智能制造产业集群", "link": "http://gov.163.com/13/1014/14/9B5DFI4T00234IGJ.html"}
{"type": "地方政务", "title": "湖北省前8月基础设施投资3020.7亿元 增长32.8%", "link": "http://gov.163.com/13/1014/14/9B5D9J1A00234IGH.html"}
{"type": "地方政务", "title": "江西政法系统充分发挥职能作用助推江西发展", "link": "http://gov.163.com/13/1014/14/9B5D7IF200234IGH.html"}
{"type": "地方政务", "title": "河北清违规公车万余辆 省级干部封存14辆越野车", "link": "http://gov.163.com/13/1014/08/9B4RKS6R00234IGH.html"}
{"type": "地方政务", "title": "癸巳年祭孔大典在山东曲阜举行", "link": "http://gov.163.com/13/0929/10/99UCC6C400234JF1.html"}
{"type": "地方政务", "title": "第三届多巴高原训练与健康国际研讨会开幕", "link": "http://gov.163.com/13/0929/10/99UC783D00234JF2.html"}
{"type": "地方政务", "title": "四川省立法保护通信设施 小区不得指定入网公司", "link": "http://gov.163.com/13/0922/14/99CQJQVH00234IGH.html"}
{"type": "地方政务", "title": "海南将投资141亿元建设国际标准旅游公路679公里", "link": "http://gov.163.com/13/0922/14/99CQE7K500234IGH.html"}
{"type": "地方政务", "title": "河南各高校要设立平抑基金确保食堂饭菜质优价廉", "link": "http://gov.163.com/13/0922/14/99CPT3S400234IGH.html"}
{"type": "地方政务", "title": "河北综合整治饶阳等县三角地带严厉打击犯罪行为", "link": "http://gov.163.com/13/0922/13/99CO8L6C00234IGH.html"}
{"type": "地方政务", "title": "定制公交上路两条线路遇堵晚点 乘客肯定舒适度", "link": "http://gov.163.com/13/0910/09/98DC8S9700234IJH.html"}
{"type": "地方政务", "title": "吉林省第六届二人转·戏剧小品艺术节将举行", "link": "http://gov.163.com/13/0906/10/98371AC300234JF1.html"}
{"type": "地方政务", "title": "福建全力扶持省级扶贫开发工作重点县加快发展", "link": "http://gov.163.com/13/0904/10/97U1I3RD00234IGH.html"}
{"type": "地方政务", "title": "北京市首批3000多辆“绿色公交车”开始交付使用", "link": "http://gov.163.com/13/0904/10/97U0O4DC00234IJH.html"}
{"type": "地方政务", "title": "市打击违建专项行动 344套“冻结”违建名单公布", "link": "http://gov.163.com/13/0902/11/97OUFC5J00234IJL.html"}
{"type": "地方政务", "title": "重庆市警方公布收集涉毒术语：溜冰海白菜象牙棒", "link": "http://gov.163.com/13/0902/10/97OR8GOS00234IGH.html"}
{"type": "地方政务", "title": "北京保监局：上半年保险市场缓中有升居全国第四", "link": "http://gov.163.com/13/0902/09/97ONSAD200234IJE.html"}
{"type": "地方政务", "title": "四部法律的有关规定拟在上海自由贸易区暂停实施", "link": "http://gov.163.com/13/0827/15/979V830Q00234IGH.html"}
{"type": "地方政务", "title": "吉林旅游商品博览会将开幕 7大资源打造特色产品", "link": "http://gov.163.com/13/0827/15/979V4R8C00234IGJ.html"}
{"type": "地方政务", "title": "装备制造成山西第三大产业 前7个月累计增长30%", "link": "http://gov.163.com/13/0827/15/979UUDRF00234IGJ.html"}
{"type": "地方政务", "title": "河北省建立多部门联动机制 查处百余条网络谣言", "link": "http://gov.163.com/13/0827/15/979TM94M00234IGH.html"}
{"type": "地方政务", "title": "天津：环城四区造林1.5万亩 绿地总面积38000亩", "link": "http://gov.163.com/13/0827/14/979TFJ4K00234IGH.html"}
{"type": "地方政务", "title": "北京市社会力量兴办福利机构获得5700多万元资助", "link": "http://gov.163.com/13/0827/09/979A0NS200234IJH.html"}
{"type": "地方政务", "title": "郭金龙走进京城社区卫生服务站听取群众意见建议", "link": "http://gov.163.com/13/0827/08/9797B3G400234IJE.html"}
{"type": "地方政务", "title": "北京市食药监将对10类高风险食品实行全程追溯", "link": "http://gov.163.com/13/0823/08/96UT546U00234IJE.html"}
{"type": "地方政务", "title": "全国22地区调最低工资 上海每月1620元居首位", "link": "http://gov.163.com/13/0823/09/96V1LPR700234IGJ.html"}
{"type": "地方政务", "title": "山西省再次压减省级公共预算支出 用于民生支出", "link": "http://gov.163.com/13/0821/13/96QA2GJ800234IGH.html"}
{"type": "地方政务", "title": "冀鼓励创办科技型企业科技人员创业 职称保留3年", "link": "http://gov.163.com/13/0821/13/96QA149400234IGJ.html"}
{"type": "地方政务", "title": "天津三年时间治理80余条河道 市区河道全部连通", "link": "http://gov.163.com/13/0821/13/96Q9T3UA00234IGH.html"}
{"type": "地方政务", "title": "北京多所大学“逼迫”新生独立报到", "link": "http://gov.163.com/13/0819/09/96KOSBDR00234IJH.html"}
{"type": "地方政务", "title": "两法衔接信息平台 执法单位不作为不立案将受查", "link": "http://gov.163.com/13/0819/09/96KMT6LN00234IJE.html"}
{"type": "地方政务", "title": "内蒙古安置就业困难人员3.9万 完成年度计划65%", "link": "http://gov.163.com/13/0815/15/96B1A37T00234IGJ.html"}
{"type": "地方政务", "title": "江苏推多种阳光制度 让保障房分配更有公正保障", "link": "http://gov.163.com/13/0815/15/96B17NT200234IGJ.html"}
{"type": "地方政务", "title": "天津五家医院新建项目进展顺利 将增病床2904张", "link": "http://gov.163.com/13/0815/15/96B13R4E00234IGH.html"}
{"type": "地方政务", "title": "北京市政府新领导班子分工确定 新班子一正八副", "link": "http://gov.163.com/13/0813/10/965DD4KJ00234IGH.html"}
{"type": "地方政务", "title": "北京：2013年汛期18种预警将第一时间告知公众", "link": "http://gov.163.com/13/0808/09/95OC8G8K00234IJE.html"}
{"type": "地方政务", "title": "福建启动规范护工管理试点工作 明年底全面推广", "link": "http://gov.163.com/13/0806/13/95JNF1U900234IGH.html"}
{"type": "地方政务", "title": "浦东企业探索产业新模式 40亿元项目落地黑龙江", "link": "http://gov.163.com/13/0806/13/95JN7ES700234IGJ.html"}
{"type": "地方政务", "title": "吉林省今年计划改造城乡危房和棚户区34.81万户", "link": "http://gov.163.com/13/0806/13/95JN46Q500234IGH.html"}
{"type": "地方政务", "title": "山西省本级行政审批流程再改革 审批时限缩短30%", "link": "http://gov.163.com/13/0806/13/95JMR5VH00234IGH.html"}
{"type": "地方政务", "title": "河北将在城市地道桥建积水深度监测装置防范内涝", "link": "http://gov.163.com/13/0806/13/95JMLPCH00234IGH.html"}
{"type": "地方政务", "title": "胡春华：维护社会稳定的根本出路是建设法治社会", "link": "http://gov.163.com/13/0806/09/95J96KKQ00234IGH.html"}
{"type": "地方政务", "title": "北京市属医院近日首次试点“公立医院托管”改革", "link": "http://gov.163.com/13/0731/08/953O54PQ00234IJH.html"}
{"type": "地方政务", "title": "中关村企业未来三年将享总授信额260亿融资服务", "link": "http://gov.163.com/13/0731/09/953OE95300234IJH.html"}
{"type": "地方政务", "title": "2013年北京市统招中考录取通知书已陆续开始投递", "link": "http://gov.163.com/13/0731/09/953OJC0400234IJH.html"}
{"type": "地方政务", "title": "首都机场等八大机场禁止以“流量管控”限制起飞", "link": "http://gov.163.com/13/0731/09/953OQSEA00234IJH.html"}
{"type": "地方政务", "title": "上半年北京市规模以上工业企业实现利润557.2亿", "link": "http://gov.163.com/13/0731/10/953TCU8700234IJM.html"}
{"type": "地方政务", "title": "北京市科协深入社区开展健康演讲、科普互动活动", "link": "http://gov.163.com/13/0731/09/953QKNP900234IJH.html"}
{"type": "地方政务", "title": "湖北拟将住房公积金纳入集体合同 保障职工权益", "link": "http://gov.163.com/13/0731/14/9549O0Q800234IGJ.html"}
{"type": "地方政务", "title": "今年上半年河南省新增小微企业贷款超过800亿元", "link": "http://gov.163.com/13/0731/14/9549LLE200234IGJ.html"}
{"type": "地方政务", "title": "山东全省政府性债务审计启动 纳入乡镇政府", "link": "http://gov.163.com/13/0731/14/9549HL0J00234IGJ.html"}
{"type": "地方政务", "title": "天津支持毕业生就业创业 半年新增就业24.6万人", "link": "http://gov.163.com/13/0731/13/95494D4C00234IGJ.html"}
{"type": "地方政务", "title": "冀出台措施助就业 低保家庭毕业生可领千元补贴", "link": "http://gov.163.com/13/0722/13/94D2K9QI00234IGJ.html"}
{"type": "地方政务", "title": "云南昆明两年内将关闭搬迁和转型升级103个市场", "link": "http://gov.163.com/13/0722/13/94D2BDMM00234IGJ.html"}
{"type": "地方政务", "title": "总结生态移民经验 打造统筹城乡配套改革升级版", "link": "http://gov.163.com/13/0722/13/94D27R8B00234IGJ.html"}
{"type": "地方政务", "title": "中国延续时间最长的古县衙署档案在益阳重见天日", "link": "http://gov.163.com/13/0722/13/94D1CIK700234IKA.html"}
{"type": "地方政务", "title": "湖北整治驾培行业突出问题 推平安交通创建活动", "link": "http://gov.163.com/13/0722/13/94D0SL6000234IGH.html"}
{"type": "地方政务", "title": "山东半岛蓝色经济战略区域构筑东部经济增长新极", "link": "http://gov.163.com/13/0722/11/94CQ60R500234IGJ.html"}
{"type": "地方政务", "title": "江西结构调整迈出新步伐 \"升级版\"经济显现雏形", "link": "http://gov.163.com/13/0722/11/94CQ2A0K00234IGJ.html"}
{"type": "地方政务", "title": "安徽警方“12110短信报警平台”有望于明年建成", "link": "http://gov.163.com/13/0722/11/94CPJ52300234IGH.html"}
{"type": "地方政务", "title": "辽省直机关开展群众路线教育 作风建设聚焦服务", "link": "http://gov.163.com/13/0722/10/94CMVB6U00234IGH.html"}
{"type": "地方政务", "title": "山西省重点工程顺利实现时间任务“双过半”目标", "link": "http://gov.163.com/13/0722/10/94CMOBS400234IGH.html"}
{"type": "地方政务", "title": "河北突出五项工作重点 积极防控H7N9禽流感疫情", "link": "http://gov.163.com/13/0722/10/94CMJTRS00234IGH.html"}
{"type": "地方政务", "title": "根据国家路网规划 天津市新增3条“国字头”高速", "link": "http://gov.163.com/13/0722/10/94CMHTEC00234IGH.html"}
{"type": "地方政务", "title": "海南三公经费降幅明显逐步建立“过紧日子”观点", "link": "http://gov.163.com/13/0718/14/942Q9Q8F00234IGH.html"}
{"type": "地方政务", "title": "河南少林寺重修普贤殿 唐代重彩画将重放异彩", "link": "http://gov.163.com/13/0718/13/942Q3BJL00234IKA.html"}
{"type": "地方政务", "title": "江西妇女议政比例不断提升 超9成女性关心天下事", "link": "http://gov.163.com/13/0718/13/942Q1H1C00234IGH.html"}
{"type": "地方政务", "title": "安徽农技推广体系建设获国家2.3亿元支持", "link": "http://gov.163.com/13/0718/13/942PUO5H00234IGJ.html"}
{"type": "地方政务", "title": "徽新石器时代聚落凌家滩遗址发现大量红烧土遗迹", "link": "http://gov.163.com/13/0718/13/942PSVDF00234IKA.html"}
{"type": "地方政务", "title": "浙上半年工业经济运行呈现“平开稳走向好”态势", "link": "http://gov.163.com/13/0718/13/942PQE0400234IGJ.html"}
{"type": "地方政务", "title": "江苏6市阶梯气价改革暂缓 涉及苏淮宿连通泰", "link": "http://gov.163.com/13/0718/13/942PC9K400234IGH.html"}
{"type": "地方政务", "title": "上半年吉林城镇新增就业36万人 完成年计划66.1%", "link": "http://gov.163.com/13/0718/13/942P9QIR00234IGJ.html"}
{"type": "地方政务", "title": "山西省交通厅造血式扶贫 筑起产业路叩开增收门", "link": "http://gov.163.com/13/0718/13/942P73N400234IGJ.html"}
{"type": "地方政务", "title": "河北省出台离校未就业高校毕业生就业促进计划", "link": "http://gov.163.com/13/0718/13/942P45S000234IGH.html"}
{"type": "地方政务", "title": "规划3年时间投860亿 完成四川芦山地震灾区重建", "link": "http://gov.163.com/13/0716/15/93TPBUDI00234IGH.html"}
{"type": "地方政务", "title": "海南省“十二五”将净增加326个调整28个加油站", "link": "http://gov.163.com/13/0716/15/93TOTCHV00234IGJ.html"}
{"type": "地方政务", "title": "多领域探索初具燎原之势 广西循环经济前景远大", "link": "http://gov.163.com/13/0716/14/93TONNT000234IGJ.html"}
{"type": "地方政务", "title": "我国第二大水电站溪洛渡水电站首台机组正式投产", "link": "http://gov.163.com/13/0716/14/93TOH0U400234IKA.html"}
{"type": "地方政务", "title": "河南焦作发现一镶嵌在东汉墓壁上的立体“楼阁”", "link": "http://gov.163.com/13/0716/14/93TOEO4H00234IKA.html"}
{"type": "地方政务", "title": "安徽省夏粮实现“十连增” 增量占全国近两成", "link": "http://gov.163.com/13/0716/14/93TO350000234IGJ.html"}
{"type": "地方政务", "title": "沪养老床位入住率约70% \"十二五\"将达到14.5万张", "link": "http://gov.163.com/13/0716/14/93TNOQDK00234IGH.html"}
{"type": "地方政务", "title": "上海卫生计生委：救护车到达10分钟内医院须接诊", "link": "http://gov.163.com/13/0716/14/93TNNI5M00234IGH.html"}
{"type": "地方政务", "title": "山西专项督查用人单位执行夏季高温津贴发放情况", "link": "http://gov.163.com/13/0716/14/93TNKBN700234IGH.html"}
{"type": "地方政务", "title": "河北省将严厉打击非正常专利申请 规范申请行为", "link": "http://gov.163.com/13/0716/14/93TNG14G00234IGH.html"}
{"type": "地方政务", "title": "津农民送菜进小区 明年社区蔬菜直销点扩至100个", "link": "http://gov.163.com/13/0716/14/93TNDETS00234IGH.html"}
{"type": "地方政务", "title": "真诚解密：了解不怕火凉茶的真正魅力", "link": "http://gov.163.com/13/0712/11/93J26FCM00234IGM.html"}
{"type": "地方政务", "title": "河南公租房新政：申请公租房没有收入、户籍限制", "link": "http://gov.163.com/13/0709/13/93BJ47D100234IGH.html"}
{"type": "地方政务", "title": "江苏：个人较重失信行为将禁考公务员、限制贷款", "link": "http://gov.163.com/13/0709/13/93BICA6600234IGH.html"}
{"type": "地方政务", "title": "山西省出台“十二条规定” 规范中小学办学行为", "link": "http://gov.163.com/13/0709/13/93BI68K700234IGH.html"}
{"type": "地方政务", "title": "青藏铁路通车7年助推青藏两省区经济稳步发展", "link": "http://gov.163.com/13/0701/08/92MF3LQD00234IGJ.html"}
{"type": "地方政务", "title": "甘肃省：酒钢循环经济与结构调整项目拉开序幕", "link": "http://gov.163.com/13/0701/08/92MEMR0G00234IGJ.html"}
{"type": "地方政务", "title": "四川：芦山灾区恢复重建中 优先使用灾区劳动者", "link": "http://gov.163.com/13/0701/08/92MDGMNL00234IGH.html"}
{"type": "地方政务", "title": "沪千余项文化活动丰富青少年暑期 95％为免费", "link": "http://gov.163.com/13/0701/08/92MDBIOV00234IKA.html"}
{"type": "地方政务", "title": "河北：134所县级公立医院药品价格降低15%", "link": "http://gov.163.com/13/0701/08/92MD8MRP00234IGH.html"}
{"type": "地方政务", "title": "酉水画廊景区开放纳客 10公里水路体验土家风俗", "link": "http://gov.163.com/13/0701/08/92MERDK200234IKA.html"}
{"type": "地方政务", "title": "打造经济发展“快车道” 抚州推进苏区振兴发展", "link": "http://gov.163.com/13/0701/08/92MEI18100234IGJ.html"}
{"type": "地方政务", "title": "云南：加快农村金融改革步伐 激发乡村建设活力", "link": "http://gov.163.com/13/0701/08/92ME5HFM00234IGJ.html"}
{"type": "地方政务", "title": "山东省安排2亿元资金开展“乡村连片治理”试点", "link": "http://gov.163.com/13/0701/08/92MDRLCH00234IGH.html"}
{"type": "地方政务", "title": "河南试点公务员绩效考核 挂钩“帽子”“票子”", "link": "http://gov.163.com/13/0701/08/92ME1JQT00234IGH.html"}
{"type": "地方政务", "title": "福建省：计划生育特殊家庭可享再生育和收养服务", "link": "http://gov.163.com/13/0701/08/92MDM1J900234IGH.html"}
{"type": "地方政务", "title": "今年1-5月江苏服务外包合同总额同比增长38.85%", "link": "http://gov.163.com/13/0701/08/92MF041L00234IKA.html"}
{"type": "地方政务", "title": "偷排废水造成事故责令关闭 津整治违法排污企业", "link": "http://gov.163.com/13/0701/08/92MDP0RM00234IGH.html"}
{"type": "地方政务", "title": "浙江\"智慧高速\"一期试运行 微博微信查即时路况", "link": "http://gov.163.com/13/0701/08/92MDUNCR00234IGH.html"}
{"type": "地方政务", "title": "青海省财政提前垫资10余亿元支持重点项目建设", "link": "http://gov.163.com/13/0701/08/92ME7Q2400234IGH.html"}
{"type": "地方政务", "title": "辽宁107个农产品加工大项目完成投资近500亿", "link": "http://gov.163.com/13/0625/08/926V14B200234IGJ.html"}
{"type": "地方政务", "title": "上海国际电影节金爵奖14部入围片彰显个性与才华", "link": "http://gov.163.com/13/0625/08/926UIOCL00234IKA.html"}
{"type": "地方政务", "title": "巴音朝鲁：建设生态经济区 开创西部发展新局面", "link": "http://gov.163.com/13/0625/08/926V3MMP00234IGJ.html"}
{"type": "地方政务", "title": "反贪“老黄牛”奋战一线28年 刮起基层反腐旋风", "link": "http://gov.163.com/13/0625/08/926UQK8100234IGH.html"}
{"type": "地方政务", "title": "广西携百余项目赴港澳招商 经贸渐入“蜜月期”", "link": "http://gov.163.com/13/0625/08/926VAB6A00234IGJ.html"}
{"type": "地方政务", "title": "贵州推动国债下乡 有效促进农民财产性收入增加", "link": "http://gov.163.com/13/0625/08/926USFO700234IGH.html"}
{"type": "地方政务", "title": "福建开展环境安全大检查 督办重大环境风险隐患", "link": "http://gov.163.com/13/0625/08/926UVAA100234IGH.html"}
{"type": "地方政务", "title": "安徽 户籍制度改革积极稳妥推进 促进毕业生创业", "link": "http://gov.163.com/13/0625/08/926VI8BK00234IGH.html"}
{"type": "地方政务", "title": "青海省青藏铁路公司提前部署 优质高效服务暑运", "link": "http://gov.163.com/13/0625/08/926VNLB700234IGH.html"}
{"type": "地方政务", "title": "陕西省将重点纠正民生领域侵害群众利益不正之风", "link": "http://gov.163.com/13/0625/08/926VDOEH00234IGH.html"}
{"type": "地方政务", "title": "山东省级为民服务热线12346开通 开展便民服务", "link": "http://gov.163.com/13/0621/13/91T85LLL00234IGH.html"}
{"type": "地方政务", "title": "江西省将用两年时间解决农村重点污染区饮水安全", "link": "http://gov.163.com/13/0621/13/91T83R1O00234IGH.html"}
{"type": "地方政务", "title": "沪公立医院改革取得初步成果 4家新院费用降20%", "link": "http://gov.163.com/13/0621/13/91T810F700234IGH.html"}
{"type": "地方政务", "title": "天津市城乡分类救助标准和范围7月1日起调整", "link": "http://gov.163.com/13/0621/11/91SVRI1L00234IGH.html"}
